usajobs/__init__.py
usajobs-0.1.5.dist-info/DESCRIPTION.rst
usajobs-0.1.5.dist-info/METADATA
usajobs-0.1.5.dist-info/RECORD
usajobs-0.1.5.dist-info/WHEEL
usajobs-0.1.5.dist-info/metadata.json
usajobs-0.1.5.dist-info/top_level.txt
