Metadata-Version: 2.0
Name: usajobs
Version: 0.1.5
Summary: Wrapper for searching usajobs.gov.
Home-page: https://github.com/brennv/usajobs
Author: brennv
Author-email: brennan@beta.build
License: MIT
Download-URL: https://github.com/brennv/usajobs/tarball/0.1.5
Keywords: usajobs usa.jobs usajobs.gov api
Platform: UNKNOWN
Classifier: Development Status :: 1 - Planning
Classifier: Intended Audience :: Developers
Classifier: License :: OSI Approved :: MIT License
Classifier: Operating System :: OS Independent
Classifier: Programming Language :: Python
Classifier: Programming Language :: Python :: 2
Classifier: Programming Language :: Python :: 2.6
Classifier: Programming Language :: Python :: 2.7
Classifier: Programming Language :: Python :: 3
Classifier: Programming Language :: Python :: 3.4
Classifier: Programming Language :: Python :: 3.5
Requires-Dist: nametupled
Requires-Dist: requests
